{
  "2024-07-26": "v1-no_tags,cost_le_10,tag_animal,active_card,prod_dec,global_req",
  "2024-07-27": "v1-raise_tr,prod_inc_megacredits,prod_dec,green_card,tag_building,cost_le_10",
  "2024-07-28": "v1-active_card,has_action,global_req,take_animal,tag_animal,prod_dec",
  "2024-07-29": "v1-cost_ge_20,green_card,prod_inc_megacredits,gain_plants,tag_earth,place_city",
  "2024-07-30": "v1-active_card,prod_dec,has_action,tag_power,cost_ge_20,take_animal",
  "2024-07-31": "v1-discount_cards,prod_dec,prod_inc_megacredits,active_card,tag_space,tag_earth",
  "2024-08-01": "v1-tag_venus,place_city,tag_earth,prod_inc_megacredits,cost_ge_20,green_card",
  "2024-08-02": "v1-take_animal,has_action,active_card,tag_animal,prod_dec_plants,prod_dec",
  "2024-08-03": "v1-take_floater,prod_dec,tag_jovian,active_card,cost_ge_20,has_action",
  "2024-08-04": "v1-prod_inc_plants,tag_city,place_city,vp,cost_ge_20,prod_dec",
  "2024-08-05": "v1-prod_inc_megacredits,prod_dec,tag_building,place_city,cost_ge_20,prod_inc_plants",
  "2024-08-06": "v1-tag_plant,prod_inc_plants,tag_city,global_req,tag_building,vp",
  "2024-08-07": "v1-prod_inc_plants,tag_venus,prod_dec_energy,cost_le_10,cost_ge_20,global_req",
  "2024-08-08": "v1-take_floater,tag_venus,req_tag_science,cost_ge_20,active_card,vp",
  "2024-08-09": "v1-draw_card_action,req_tag_science,take_animal,vp,has_action,active_card",
  "2024-08-10": "v1-prod_inc_steel,prod_inc_heat,gain_plants,green_card,cost_le_10,tag_building",
  "2024-08-11": "v1-rm_plants,raise_tr,place_ocean,cost_ge_20,tag_space,event_card",
  "2024-08-12": "v1-draw_card,raise_tr,gain_plants,event_card,tag_space,vp",
  "2024-08-13": "v1-prod_inc_plants,tag_venus,tag_city,vp,global_req,cost_ge_20",
  "2024-08-14": "v1-tag_city,tag_earth,tag_venus,tag_space,prod_inc_megacredits,green_card",
  "2024-08-15": "v1-prod_inc_heat,tag_city,tag_earth,cost_ge_20,tag_space,green_card",
  "2024-08-16": "v1-req_tag_science,has_action,tag_building,tag_power,tag_science,cost_ge_20",
  "2024-08-17": "v1-prod_dec_energy,raise_tr,prod_inc_plants,vp,cost_le_10,cost_ge_20",
  "2024-08-18": "v1-prod_inc_titanium,place_city,tag_power,tag_building,prod_dec,vp",
  "2024-08-19": "v1-req_tag_earth,gain_plants,draw_card,green_card,tag_earth,cost_le_10",
  "2024-08-20": "v1-green_card,cost_le_10,vp,req_tag_earth,tag_venus,draw_card",
  "2024-08-21": "v1-take_animal,take_microbe,no_tags,global_req,has_action,active_card",
  "2024-08-22": "v1-take_microbe,prod_inc_plants,tag_plant,vp,global_req,tag_microbe",
  "2024-08-23": "v1-prod_dec_plants,prod_dec,take_animal,tag_animal,global_req,has_action",
  "2024-08-24": "v1-prod_dec,vp,global_req,prod_dec_plants,tag_city,tag_power",
  "2024-08-25": "v1-has_action,vp,active_card,take_animal,tag_power,no_tags",
  "2024-08-26": "v1-vp,has_action,active_card,prod_dec_plants,take_floater,tag_power",
  "2024-08-27": "v1-no_tags,tag_animal,tag_power,prod_dec,active_card,vp",
  "2024-08-28": "v1-tag_power,prod_inc_energy,tag_science,req_tag_science,tag_building,global_req",
  "2024-08-29": "v1-active_card,tag_space,cost_ge_20,prod_inc_megacredits,tag_venus,tag_earth",
  "2024-08-30": "v1-tag_building,global_req,vp,place_city,gain_plants,prod_inc_energy",
  "2024-08-31": "v1-prod_inc_energy,tag_plant,tag_microbe,cost_le_10,vp,global_req",
  "2024-09-01": "v1-take_microbe,tag_plant,prod_inc_plants,global_req,tag_microbe,vp",
  "2024-09-02": "v1-rm_plants,place_ocean,gain_plants,cost_ge_20,event_card,tag_space",
  "2024-09-03": "v1-prod_inc_megacredits,tag_building,prod_dec,tag_city,global_req,place_city",
  "2024-09-04": "v1-global_req,cost_le_10,vp,tag_animal,gain_plants,take_animal",
  "2024-09-05": "v1-cost_ge_20,tag_space,green_card,place_city,req_tag_science,prod_inc_heat",
  "2024-09-06": "v1-active_card,gain_plants,prod_dec,prod_inc_megacredits,tag_earth,cost_ge_20",
  "2024-09-07": "v1-place_ocean,prod_dec,prod_inc_megacredits,no_tags,cost_ge_20,tag_space",
  "2024-09-08": "v1-active_card,global_req,prod_dec,prod_dec_plants,prod_inc_megacredits,take_animal",
  "2024-09-09": "v1-tag_microbe,tag_building,global_req,tag_science,prod_inc_plants,tag_plant",
  "2024-09-10": "v1-draw_card_action,tag_power,prod_inc_energy,tag_building,tag_science,vp",
  "2024-09-11": "v1-raise_tr,prod_inc_megacredits,prod_dec,no_tags,prod_inc_plants,cost_ge_20",
  "2024-09-12": "v1-draw_card,prod_inc_titanium,tag_venus,tag_space,vp,green_card",
  "2024-09-13": "v1-draw_card,req_tag_science,tag_venus,cost_le_10,tag_space,green_card",
  "2024-09-14": "v1-place_ocean,prod_dec,raise_tr,no_tags,tag_space,cost_ge_20",
  "2024-09-15": "v1-green_card,vp,cost_le_10,tag_microbe,req_tag_earth,gain_plants",
  "2024-09-16": "v1-cost_ge_20,tag_earth,prod_inc_megacredits,gain_plants,active_card,prod_dec",
  "2024-09-17": "v1-cost_le_10,vp,green_card,raise_tr,req_tag_earth,tag_microbe",
  "2024-09-18": "v1-gain_plants,rm_plants,raise_tr,cost_ge_20,event_card,tag_space",
  "2024-09-19": "v1-tag_plant,global_req,prod_inc_plants,prod_inc_megacredits,tag_microbe,tag_building",
  "2024-09-20": "v1-global_req,prod_dec,cost_ge_20,prod_inc_megacredits,prod_inc_plants,tag_city",
  "2024-09-21": "v1-take_microbe,tag_microbe,tag_venus,global_req,active_card,cost_le_10",
  "2024-09-22": "v1-tag_power,draw_card_action,cost_ge_20,tag_building,has_action,active_card",
  "2024-09-23": "v1-tag_space,vp,cost_le_10,tag_power,draw_card,tag_venus",
  "2024-09-24": "v1-req_tag_science,discount_cards,tag_microbe,tag_science,active_card,cost_le_10",
  "2024-09-25": "v1-draw_card_action,req_tag_science,tag_microbe,active_card,tag_science,has_action",
  "2024-09-26": "v1-take_animal,take_microbe,tag_power,global_req,has_action,vp",
  "2024-09-27": "v1-req_tag_earth,gain_plants,draw_card,tag_earth,cost_le_10,green_card",
  "2024-09-28": "v1-draw_card,discount_cards,has_action,tag_science,tag_earth,tag_space",
  "2024-09-29": "v1-prod_inc_plants,gain_plants,place_city,vp,prod_inc_megacredits,tag_building",
  "2024-09-30": "v1-tag_city,prod_inc_titanium,raise_tr,tag_building,vp,cost_ge_20",
  "2024-10-01": "v1-discount_cards,tag_microbe,draw_card,tag_science,vp,cost_le_10",
  "2024-10-02": "v1-vp,green_card,cost_le_10,req_tag_science,req_tag_earth,raise_tr",
  "2024-10-03": "v1-place_ocean,prod_dec,has_action,tag_space,cost_ge_20,no_tags",
  "2024-10-04": "v1-vp,cost_le_10,global_req,take_animal,tag_power,gain_plants",
  "2024-10-05": "v1-prod_inc_steel,gain_plants,raise_tr,tag_building,green_card,cost_le_10",
  "2024-10-06": "v1-prod_inc_steel,prod_inc_heat,gain_plants,tag_building,cost_le_10,green_card",
  "2024-10-07": "v1-prod_dec_energy,tag_animal,tag_microbe,active_card,global_req,cost_le_10",
  "2024-10-08": "v1-prod_dec,active_card,has_action,tag_earth,take_animal,cost_ge_20",
  "2024-10-09": "v1-prod_dec_energy,cost_ge_20,prod_inc_megacredits,place_city,active_card,tag_city",
  "2024-10-10": "v1-place_city,prod_dec_energy,prod_inc_plants,prod_inc_megacredits,global_req,vp",
  "2024-10-11": "v1-has_action,vp,global_req,take_microbe,prod_dec_plants,take_animal",
  "2024-10-12": "v1-tag_power,tag_science,cost_ge_20,tag_building,req_tag_science,has_action",
  "2024-10-13": "v1-prod_inc_megacredits,prod_dec,prod_dec_energy,active_card,place_city,global_req",
  "2024-10-14": "v1-prod_dec_energy,tag_earth,tag_venus,cost_ge_20,active_card,prod_inc_megacredits",
  "2024-10-15": "v1-tag_venus,tag_city,gain_plants,green_card,tag_space,global_req",
  "2024-10-16": "v1-take_microbe,tag_plant,prod_inc_plants,cost_le_10,tag_microbe,global_req",
  "2024-10-17": "v1-prod_inc_titanium,req_tag_science,raise_tr,tag_space,green_card,cost_ge_20",
  "2024-10-18": "v1-prod_inc_heat,place_city,prod_inc_titanium,tag_space,prod_dec,tag_building",
  "2024-10-19": "v1-tag_plant,tag_venus,tag_animal,global_req,cost_le_10,vp",
  "2024-10-20": "v1-vp,tag_building,tag_space,prod_inc_titanium,prod_inc_energy,raise_tr",
  "2024-10-21": "v1-no_tags,tag_animal,prod_dec_plants,vp,prod_dec,active_card",
  "2024-10-22": "v1-req_tag_science,tag_building,global_req,tag_power,tag_science,prod_inc_energy",
  "2024-10-23": "v1-tag_animal,has_action,global_req,take_animal,prod_dec_plants,prod_dec",
  "2024-10-24": "v1-tag_city,active_card,prod_inc_megacredits,prod_dec_energy,cost_ge_20,prod_dec",
  "2024-10-25": "v1-place_ocean,has_action,prod_inc_megacredits,tag_space,no_tags,cost_ge_20",
  "2024-10-26": "v1-event_card,cost_ge_20,tag_space,rm_plants,gain_plants,place_ocean",
  "2024-10-27": "v1-prod_dec_energy,tag_power,take_animal,global_req,vp,active_card",
  "2024-10-28": "v1-global_req,tag_space,prod_dec,prod_inc_energy,prod_inc_megacredits,place_city",
  "2024-10-29": "v1-draw_card_action,req_tag_science,tag_microbe,has_action,vp,tag_science",
  "2024-10-30": "v1-prod_dec_plants,no_tags,tag_animal,vp,global_req,active_card",
  "2024-10-31": "v1-cost_le_10,active_card,vp,req_tag_science,discount_cards,prod_dec_energy",
  "2024-11-01": "v1-draw_card_action,no_tags,tag_microbe,vp,has_action,active_card",
  "2024-11-02": "v1-raise_tr,prod_inc_megacredits,prod_dec,cost_ge_20,no_tags,prod_inc_plants",
  "2024-11-03": "v1-draw_card_action,tag_microbe,req_tag_science,tag_science,active_card,vp",
  "2024-11-04": "v1-active_card,vp,tag_science,tag_power,discount_cards,tag_microbe",
  "2024-11-05": "v1-place_ocean,has_action,raise_tr,tag_space,no_tags,cost_ge_20",
  "2024-11-06": "v1-tag_venus,tag_jovian,cost_ge_20,take_floater,has_action,active_card",
  "2024-11-07": "v1-take_floater,cost_ge_20,tag_space,tag_venus,has_action,tag_jovian",
  "2024-11-08": "v1-no_tags,prod_dec,tag_venus,prod_inc_megacredits,has_action,global_req",
  "2024-11-09": "v1-has_action,vp,active_card,tag_animal,tag_venus,no_tags",
  "2024-11-10": "v1-rm_plants,raise_tr,gain_plants,cost_ge_20,event_card,tag_space",
  "2024-11-11": "v1-prod_dec,global_req,vp,tag_power,place_city,tag_animal",
  "2024-11-12": "v1-tag_plant,place_city,tag_city,vp,tag_building,prod_inc_megacredits",
  "2024-11-13": "v1-event_card,tag_space,cost_ge_20,place_ocean,tag_earth,rm_plants",
  "2024-11-14": "v1-req_tag_earth,gain_plants,draw_card,tag_earth,vp,green_card",
  "2024-11-15": "v1-cost_ge_20,vp,green_card,req_tag_science,place_city,gain_plants",
  "2024-11-16": "v1-active_card,tag_space,has_action,tag_power,tag_jovian,tag_venus",
  "2024-11-17": "v1-event_card,draw_card,discount_cards,vp,tag_earth,tag_science",
  "2024-11-18": "v1-take_floater,req_tag_science,tag_venus,cost_ge_20,vp,has_action",
  "2024-11-19": "v1-prod_dec_energy,tag_earth,tag_venus,prod_inc_megacredits,cost_ge_20,active_card",
  "2024-11-20": "v1-raise_tr,draw_card,gain_plants,vp,event_card,green_card",
  "2024-11-21": "v1-gain_plants,tag_building,prod_inc_megacredits,tag_plant,global_req,prod_inc_plants",
  "2024-11-22": "v1-tag_earth,tag_space,tag_science,discount_cards,has_action,draw_card",
  "2024-11-23": "v1-discount_cards,tag_power,draw_card,cost_le_10,tag_science,tag_space",
  "2024-11-24": "v1-active_card,has_action,prod_dec,no_tags,tag_earth,take_animal",
  "2024-11-25": "v1-has_action,tag_power,prod_inc_energy,prod_dec,tag_space,req_tag_science",
  "2024-11-26": "v1-tag_science,tag_earth,vp,event_card,draw_card,discount_cards",
  "2024-11-27": "v1-prod_inc_plants,tag_city,place_city,prod_inc_megacredits,vp,prod_dec",
  "2024-11-28": "v1-tag_plant,prod_inc_plants,global_req,tag_microbe,tag_building,gain_plants",
  "2024-11-29": "v1-take_microbe,tag_animal,prod_dec_plants,has_action,active_card,cost_le_10",
  "2024-11-30": "v1-req_tag_science,tag_microbe,tag_venus,green_card,cost_le_10,active_card",
  "2024-12-01": "v1-rm_plants,place_ocean,raise_tr,event_card,cost_ge_20,tag_space",
  "2024-12-02": "v1-tag_space,cost_ge_20,no_tags,place_ocean,prod_inc_megacredits,raise_tr",
  "2024-12-03": "v1-event_card,cost_le_10,green_card,raise_tr,draw_card,gain_plants",
  "2024-12-04": "v1-req_tag_earth,gain_plants,discount_cards,cost_le_10,tag_earth,vp",
  "2024-12-05": "v1-global_req,tag_building,tag_space,tag_science,prod_inc_energy,gain_plants",
  "2024-12-06": "v1-discount_cards,draw_card,gain_plants,tag_space,tag_earth,vp",
  "2024-12-07": "v1-tag_animal,global_req,has_action,take_animal,prod_dec_plants,prod_dec",
  "2024-12-08": "v1-rm_plants,gain_plants,place_ocean,cost_ge_20,tag_space,event_card",
  "2024-12-09": "v1-prod_dec,active_card,has_action,tag_earth,take_animal,tag_power",
  "2024-12-10": "v1-place_city,tag_city,gain_plants,tag_building,global_req,green_card",
  "2024-12-11": "v1-prod_inc_heat,gain_plants,prod_inc_plants,cost_ge_20,tag_building,cost_le_10",
  "2024-12-12": "v1-take_animal,tag_animal,tag_power,cost_le_10,active_card,has_action",
  "2024-12-13": "v1-prod_inc_plants,prod_inc_heat,gain_plants,tag_building,cost_ge_20,cost_le_10",
  "2024-12-14": "v1-tag_city,place_city,prod_inc_heat,cost_ge_20,tag_building,green_card",
  "2024-12-15": "v1-discount_cards,tag_power,tag_venus,vp,active_card,tag_space",
  "2024-12-16": "v1-prod_inc_steel,gain_plants,raise_tr,cost_le_10,green_card,tag_building",
  "2024-12-17": "v1-cost_le_10,vp,global_req,gain_plants,tag_microbe,tag_plant",
  "2024-12-18": "v1-event_card,green_card,tag_space,draw_card,gain_plants,tag_earth",
  "2024-12-19": "v1-prod_inc_titanium,tag_power,prod_inc_energy,prod_dec,vp,tag_space",
  "2024-12-20": "v1-tag_science,tag_power,tag_venus,global_req,has_action,tag_space",
  "2024-12-21": "v1-active_card,has_action,cost_le_10,tag_power,tag_animal,req_tag_science",
  "2024-12-22": "v1-take_floater,tag_venus,req_tag_science,vp,has_action,cost_ge_20",
  "2024-12-23": "v1-prod_dec_plants,global_req,has_action,take_animal,tag_animal,prod_dec",
  "2024-12-24": "v1-take_animal,place_city,tag_power,vp,prod_dec,global_req",
  "2024-12-25": "v1-prod_inc_steel,gain_plants,raise_tr,green_card,tag_building,cost_le_10",
  "2024-12-26": "v1-green_card,tag_space,cost_ge_20,prod_inc_heat,tag_earth,tag_city",
  "2024-12-27": "v1-take_microbe,prod_inc_plants,tag_plant,cost_le_10,tag_microbe,global_req",
  "2024-12-28": "v1-tag_jovian,tag_venus,cost_ge_20,has_action,active_card,take_floater",
  "2024-12-29": "v1-no_tags,prod_dec_plants,cost_ge_20,active_card,prod_dec,has_action",
  "2024-12-30": "v1-tag_earth,vp,cost_le_10,discount_cards,req_tag_earth,draw_card",
  "2024-12-31": "v1-prod_inc_plants,cost_ge_20,no_tags,prod_dec,raise_tr,prod_inc_megacredits",
  "2025-01-01": "v1-global_req,prod_dec,vp,prod_dec_plants,place_city,tag_city",
  "2025-01-02": "v1-active_card,has_action,cost_ge_20,tag_jovian,req_tag_science,take_floater",
  "2025-01-03": "v1-take_animal,tag_animal,prod_dec,has_action,global_req,prod_dec_plants",
  "2025-01-04": "v1-discount_cards,gain_plants,req_tag_science,tag_space,vp,cost_le_10",
  "2025-01-05": "v1-green_card,tag_space,cost_le_10,draw_card,prod_inc_heat,raise_tr",
  "2025-01-06": "v1-draw_card,gain_plants,raise_tr,tag_space,green_card,vp",
  "2025-01-07": "v1-tag_plant,prod_inc_plants,global_req,tag_microbe,gain_plants,prod_inc_megacredits",
  "2025-01-08": "v1-prod_dec,cost_ge_20,tag_space,tag_earth,prod_inc_heat,prod_inc_titanium",
  "2025-01-09": "v1-tag_space,event_card,cost_ge_20,rm_plants,gain_plants,place_ocean",
  "2025-01-10": "v1-cost_ge_20,tag_space,no_tags,place_ocean,prod_inc_megacredits,raise_tr",
  "2025-01-11": "v1-place_city,prod_inc_titanium,gain_plants,tag_building,cost_ge_20,vp",
  "2025-01-12": "v1-has_action,tag_building,req_tag_science,tag_science,cost_ge_20,tag_power",
  "2025-01-13": "v1-event_card,cost_ge_20,tag_space,rm_plants,raise_tr,tag_earth",
  "2025-01-14": "v1-take_animal,tag_animal,prod_dec,global_req,prod_dec_plants,has_action",
  "2025-01-15": "v1-tag_building,prod_dec,tag_space,tag_city,prod_inc_titanium,prod_inc_energy",
  "2025-01-16": "v1-place_city,gain_plants,tag_city,green_card,prod_inc_megacredits,tag_space",
  "2025-01-17": "v1-tag_space,green_card,cost_ge_20,req_tag_science,tag_jovian,place_city",
  "2025-01-18": "v1-prod_inc_plants,cost_ge_20,global_req,tag_building,gain_plants,prod_inc_megacredits",
  "2025-01-19": "v1-global_req,vp,prod_dec,prod_dec_plants,tag_animal,place_city",
  "2025-01-20": "v1-prod_inc_steel,gain_plants,raise_tr,tag_building,cost_le_10,green_card",
  "2025-01-21": "v1-take_floater,has_action,active_card,tag_jovian,cost_ge_20,tag_venus",
  "2025-01-22": "v1-tag_power,cost_ge_20,tag_science,has_action,tag_building,req_tag_science",
  "2025-01-23": "v1-prod_inc_heat,prod_inc_plants,raise_tr,cost_ge_20,cost_le_10,tag_building",
  "2025-01-24": "v1-has_action,tag_city,place_city,prod_dec,cost_ge_20,tag_space",
  "2025-01-25": "v1-prod_inc_titanium,tag_power,place_city,tag_space,prod_dec,vp",
  "2025-01-26": "v1-tag_animal,tag_power,req_tag_science,cost_le_10,vp,active_card",
  "2025-01-27": "v1-prod_inc_titanium,active_card,has_action,tag_jovian,cost_ge_20,prod_dec",
  "2025-01-28": "v1-place_city,raise_tr,prod_inc_energy,vp,tag_building,tag_space",
  "2025-01-29": "v1-place_ocean,raise_tr,rm_plants,event_card,tag_space,cost_ge_20",
  "2025-01-30": "v1-raise_tr,gain_plants,cost_ge_20,event_card,prod_inc_plants,tag_building",
  "2025-01-31": "v1-place_ocean,raise_tr,rm_plants,cost_ge_20,event_card,tag_space",
  "2025-02-01": "v1-active_card,has_action,prod_dec,cost_ge_20,no_tags,tag_animal",
  "2025-02-02": "v1-event_card,discount_cards,draw_card,vp,tag_earth,tag_science",
  "2025-02-03": "v1-tag_venus,tag_city,gain_plants,green_card,prod_inc_megacredits,vp",
  "2025-02-04": "v1-prod_inc_megacredits,vp,global_req,no_tags,prod_dec_energy,gain_plants",
  "2025-02-05": "v1-take_floater,tag_space,cost_ge_20,has_action,tag_venus,tag_jovian",
  "2025-02-06": "v1-cost_ge_20,green_card,tag_space,place_city,prod_inc_heat,tag_venus",
  "2025-02-07": "v1-take_microbe,req_tag_science,tag_power,has_action,vp,cost_le_10",
  "2025-02-08": "v1-place_ocean,gain_plants,raise_tr,tag_space,cost_ge_20,event_card",
  "2025-02-09": "v1-cost_ge_20,global_req,prod_dec_energy,prod_inc_megacredits,tag_city,place_city",
  "2025-02-10": "v1-tag_earth,tag_space,cost_ge_20,prod_inc_megacredits,gain_plants,has_action",
  "2025-02-11": "v1-cost_le_10,vp,global_req,tag_microbe,prod_inc_plants,take_animal",
  "2025-02-12": "v1-event_card,tag_space,cost_ge_20,gain_plants,place_ocean,raise_tr",
  "2025-02-13": "v1-tag_animal,no_tags,take_microbe,active_card,vp,global_req",
  "2025-02-14": "v1-no_tags,prod_dec_plants,tag_animal,has_action,vp,prod_dec",
  "2025-02-15": "v1-req_tag_science,tag_power,draw_card_action,vp,tag_science,has_action",
  "2025-02-16": "v1-prod_inc_megacredits,vp,global_req,prod_inc_plants,prod_dec_energy,gain_plants",
  "2025-02-17": "v1-req_tag_science,tag_microbe,draw_card,green_card,tag_science,vp",
  "2025-02-18": "v1-gain_plants,tag_city,place_city,global_req,vp,cost_ge_20",
  "2025-02-19": "v1-tag_animal,tag_power,prod_dec_plants,prod_dec,vp,active_card",
  "2025-02-20": "v1-tag_space,tag_science,prod_dec,has_action,prod_inc_energy,tag_power",
  "2025-02-21": "v1-take_floater,req_tag_science,tag_venus,has_action,cost_ge_20,vp",
  "2025-02-22": "v1-prod_dec,vp,global_req,no_tags,tag_city,tag_power",
  "2025-02-23": "v1-draw_card,discount_cards,gain_plants,tag_earth,tag_space,vp",
  "2025-02-24": "v1-tag_jovian,tag_venus,tag_earth,active_card,cost_ge_20,green_card",
  "2025-02-25": "v1-global_req,prod_dec,vp,no_tags,prod_inc_energy,prod_dec_plants",
  "2025-02-26": "v1-tag_science,tag_power,cost_ge_20,has_action,tag_building,req_tag_science",
  "2025-02-27": "v1-tag_building,tag_space,cost_ge_20,place_city,prod_inc_heat,raise_tr",
  "2025-02-28": "v1-take_animal,tag_animal,prod_dec,has_action,prod_dec_plants,active_card",
  "2025-03-01": "v1-prod_inc_heat,prod_inc_energy,tag_city,prod_dec,tag_space,tag_building",
  "2025-03-02": "v1-cost_ge_20,cost_le_10,vp,raise_tr,tag_venus,prod_dec_energy",
  "2025-03-03": "v1-tag_jovian,tag_venus,req_tag_science,green_card,tag_space,has_action",
  "2025-03-04": "v1-tag_power,draw_card_action,discount_cards,tag_science,active_card,vp",
  "2025-03-05": "v1-place_city,prod_inc_heat,tag_city,prod_dec,tag_building,green_card",
  "2025-03-06": "v1-tag_earth,tag_science,tag_space,discount_cards,has_action,draw_card",
  "2025-03-07": "v1-vp,active_card,cost_le_10,tag_venus,take_microbe,discount_cards",
  "2025-03-08": "v1-cost_le_10,green_card,vp,tag_venus,req_tag_earth,gain_plants",
  "2025-03-09": "v1-take_animal,take_microbe,req_tag_science,active_card,has_action,cost_le_10",
  "2025-03-10": "v1-tag_building,prod_inc_plants,event_card,raise_tr,cost_ge_20,gain_plants",
  "2025-03-11": "v1-place_city,prod_inc_heat,tag_earth,tag_space,prod_dec,green_card",
  "2025-03-12": "v1-prod_inc_megacredits,vp,global_req,prod_dec_energy,tag_plant,gain_plants",
  "2025-03-13": "v1-has_action,prod_inc_energy,tag_power,tag_science,tag_space,prod_dec",
  "2025-03-14": "v1-prod_dec,prod_dec_plants,tag_animal,active_card,take_animal,has_action",
  "2025-03-15": "v1-tag_plant,global_req,prod_inc_plants,gain_plants,prod_inc_megacredits,tag_microbe",
  "2025-03-16": "v1-prod_dec_energy,prod_inc_plants,gain_plants,prod_inc_megacredits,cost_le_10,global_req",
  "2025-03-17": "v1-raise_tr,prod_dec,prod_inc_megacredits,cost_ge_20,no_tags,tag_space",
  "2025-03-18": "v1-tag_building,vp,prod_dec,prod_inc_titanium,prod_inc_plants,prod_inc_energy",
  "2025-03-19": "v1-prod_inc_plants,active_card,has_action,cost_ge_20,tag_microbe,prod_dec",
  "2025-03-20": "v1-take_microbe,tag_plant,prod_inc_plants,tag_microbe,cost_le_10,global_req",
  "2025-03-21": "v1-green_card,vp,tag_space,place_city,tag_city,prod_inc_titanium",
  "2025-03-22": "v1-prod_inc_plants,place_city,tag_city,tag_building,prod_inc_megacredits,cost_ge_20",
  "2025-03-23": "v1-no_tags,tag_earth,tag_animal,prod_dec,active_card,has_action",
  "2025-03-24": "v1-req_tag_earth,gain_plants,draw_card,green_card,vp,tag_earth",
  "2025-03-25": "v1-prod_dec,take_animal,tag_animal,prod_dec_plants,global_req,has_action",
  "2025-03-26": "v1-prod_inc_plants,tag_power,tag_plant,tag_building,global_req,cost_le_10",
  "2025-03-27": "v1-take_animal,prod_dec_plants,prod_dec,has_action,tag_animal,global_req",
  "2025-03-28": "v1-tag_science,tag_space,vp,discount_cards,prod_inc_energy,tag_power",
  "2025-03-29": "v1-event_card,prod_inc_plants,tag_building,gain_plants,cost_ge_20,raise_tr",
  "2025-03-30": "v1-tag_plant,global_req,prod_inc_plants,prod_inc_megacredits,gain_plants,tag_microbe",
  "2025-03-31": "v1-global_req,active_card,has_action,no_tags,tag_power,take_microbe",
  "2025-04-01": "v1-prod_inc_energy,tag_power,prod_inc_heat,tag_building,tag_space,prod_dec",
  "2025-04-02": "v1-cost_ge_20,tag_space,prod_inc_megacredits,tag_earth,prod_dec,place_city",
  "2025-04-03": "v1-prod_inc_titanium,prod_inc_megacredits,tag_earth,tag_space,cost_ge_20,prod_dec",
  "2025-04-04": "v1-req_tag_earth,gain_plants,draw_card,green_card,cost_le_10,tag_earth",
  "2025-04-05": "v1-prod_inc_energy,tag_venus,tag_city,global_req,tag_space,vp",
  "2025-04-06": "v1-tag_earth,tag_city,place_city,green_card,prod_inc_megacredits,cost_ge_20",
  "2025-04-07": "v1-tag_venus,tag_power,tag_microbe,has_action,vp,active_card",
  "2025-04-08": "v1-take_floater,req_tag_science,prod_dec_energy,active_card,cost_ge_20,vp",
  "2025-04-09": "v1-tag_microbe,draw_card_action,req_tag_science,active_card,tag_science,has_action",
  "2025-04-10": "v1-take_animal,tag_power,tag_animal,prod_dec,global_req,cost_le_10",
  "2025-04-11": "v1-prod_dec,cost_ge_20,tag_space,place_city,has_action,prod_inc_titanium",
  "2025-04-12": "v1-prod_dec,active_card,has_action,tag_animal,tag_earth,take_animal",
  "2025-04-13": "v1-prod_inc_heat,raise_tr,prod_inc_titanium,green_card,tag_space,tag_building",
  "2025-04-14": "v1-event_card,cost_ge_20,tag_space,gain_plants,tag_earth,place_ocean",
  "2025-04-15": "v1-active_card,has_action,prod_dec,tag_animal,cost_ge_20,tag_earth",
  "2025-04-16": "v1-tag_venus,prod_dec,prod_dec_energy,active_card,prod_inc_megacredits,cost_ge_20",
  "2025-04-17": "v1-tag_animal,active_card,has_action,prod_dec_plants,prod_dec,take_animal",
  "2025-04-18": "v1-prod_dec_energy,tag_city,gain_plants,vp,cost_ge_20,global_req",
  "2025-04-19": "v1-discount_cards,draw_card,has_action,tag_earth,tag_science,tag_space",
  "2025-04-20": "v1-global_req,tag_city,cost_ge_20,prod_dec,prod_dec_energy,tag_building",
  "2025-04-21": "v1-rm_plants,tag_earth,gain_plants,tag_space,event_card,cost_ge_20",
  "2025-04-22": "v1-tag_venus,place_city,gain_plants,green_card,prod_inc_megacredits,global_req",
  "2025-04-23": "v1-tag_earth,vp,cost_le_10,req_tag_earth,draw_card,gain_plants",
  "2025-04-24": "v1-draw_card_action,tag_microbe,tag_power,tag_science,active_card,has_action",
  "2025-04-25": "v1-cost_ge_20,global_req,prod_dec,prod_inc_megacredits,prod_inc_plants,place_city",
  "2025-04-26": "v1-has_action,vp,active_card,tag_venus,draw_card_action,tag_animal",
  "2025-04-27": "v1-prod_dec_energy,tag_microbe,take_animal,cost_le_10,active_card,global_req",
  "2025-04-28": "v1-prod_inc_steel,gain_plants,prod_inc_heat,green_card,cost_le_10,tag_building",
  "2025-04-29": "v1-place_ocean,prod_inc_megacredits,has_action,no_tags,tag_space,cost_ge_20",
  "2025-04-30": "v1-place_ocean,raise_tr,gain_plants,cost_ge_20,event_card,tag_space",
  "2025-05-01": "v1-event_card,draw_card,discount_cards,tag_science,vp,tag_earth",
  "2025-05-02": "v1-prod_dec_plants,no_tags,prod_inc_megacredits,active_card,prod_dec,global_req",
  "2025-05-03": "v1-tag_building,prod_dec,prod_inc_megacredits,prod_inc_plants,cost_ge_20,tag_city",
  "2025-05-04": "v1-prod_inc_steel,gain_plants,prod_inc_heat,tag_building,green_card,cost_le_10",
  "2025-05-05": "v1-tag_science,active_card,vp,draw_card_action,discount_cards,tag_microbe",
  "2025-05-06": "v1-prod_inc_megacredits,prod_dec,gain_plants,tag_space,global_req,prod_inc_plants",
  "2025-05-07": "v1-vp,prod_inc_megacredits,global_req,no_tags,prod_dec_energy,tag_plant",
  "2025-05-08": "v1-tag_earth,tag_science,vp,event_card,draw_card,discount_cards",
  "2025-05-09": "v1-rm_plants,place_ocean,gain_plants,tag_space,cost_ge_20,event_card",
  "2025-05-10": "v1-prod_inc_heat,tag_earth,prod_inc_titanium,prod_dec,green_card,tag_space",
  "2025-05-11": "v1-tag_animal,prod_dec,take_animal,has_action,prod_dec_plants,global_req",
  "2025-05-12": "v1-raise_tr,tag_microbe,gain_plants,green_card,cost_le_10,prod_inc_plants",
  "2025-05-13": "v1-prod_dec_plants,prod_dec,take_animal,tag_animal,active_card,has_action",
  "2025-05-14": "v1-take_animal,prod_dec_plants,prod_dec,tag_animal,active_card,has_action",
  "2025-05-15": "v1-take_microbe,prod_dec_plants,tag_animal,vp,cost_le_10,has_action",
  "2025-05-16": "v1-no_tags,tag_space,cost_ge_20,place_ocean,prod_dec,has_action",
  "2025-05-17": "v1-green_card,cost_ge_20,tag_space,tag_city,req_tag_science,tag_earth",
  "2025-05-18": "v1-take_animal,prod_inc_plants,tag_power,cost_le_10,prod_dec,global_req",
  "2025-05-19": "v1-prod_inc_steel,prod_inc_heat,raise_tr,tag_building,green_card,cost_le_10",
  "2025-05-20": "v1-take_animal,active_card,global_req,prod_dec_plants,tag_animal,prod_dec",
  "2025-05-21": "v1-req_tag_science,draw_card_action,tag_power,active_card,has_action,tag_science",
  "2025-05-22": "v1-tag_jovian,tag_venus,has_action,take_floater,cost_ge_20,tag_space",
  "2025-05-23": "v1-take_animal,tag_plant,tag_venus,vp,cost_le_10,global_req",
  "2025-05-24": "v1-prod_dec_energy,prod_dec,prod_inc_megacredits,cost_ge_20,place_city,active_card"
}
